{
  "type": "File",
  "start": 0,
  "end": 458,
  "loc": {
    "start": {
      "line": 1,
      "column": 0
    },
    "end": {
      "line": 20,
      "column": 0
    }
  },
  "program": {
    "type": "Program",
    "start": 0,
    "end": 458,
    "loc": {
      "start": {
        "line": 1,
        "column": 0
      },
      "end": {
        "line": 20,
        "column": 0
      }
    },
    "sourceType": "module",
    "body": [
      {
        "type": "ImportDeclaration",
        "start": 0,
        "end": 39,
        "loc": {
          "start": {
            "line": 1,
            "column": 0
          },
          "end": {
            "line": 1,
            "column": 39
          }
        },
        "specifiers": [
          {
            "type": "ImportDefaultSpecifier",
            "start": 7,
            "end": 16,
            "loc": {
              "start": {
                "line": 1,
                "column": 7
              },
              "end": {
                "line": 1,
                "column": 16
              }
            },
            "local": {
              "type": "Identifier",
              "start": 7,
              "end": 16,
              "loc": {
                "start": {
                  "line": 1,
                  "column": 7
                },
                "end": {
                  "line": 1,
                  "column": 16
                },
                "identifierName": "byte2char"
              },
              "name": "byte2char"
            }
          }
        ],
        "source": {
          "type": "StringLiteral",
          "start": 22,
          "end": 38,
          "loc": {
            "start": {
              "line": 1,
              "column": 22
            },
            "end": {
              "line": 1,
              "column": 38
            }
          },
          "extra": {
            "rawValue": "./byte2char.js",
            "raw": "'./byte2char.js'"
          },
          "value": "./byte2char.js"
        }
      },
      {
        "type": "ImportDeclaration",
        "start": 40,
        "end": 93,
        "loc": {
          "start": {
            "line": 2,
            "column": 0
          },
          "end": {
            "line": 2,
            "column": 53
          }
        },
        "specifiers": [
          {
            "type": "ImportDefaultSpecifier",
            "start": 47,
            "end": 63,
            "loc": {
              "start": {
                "line": 2,
                "column": 7
              },
              "end": {
                "line": 2,
                "column": 23
              }
            },
            "local": {
              "type": "Identifier",
              "start": 47,
              "end": 63,
              "loc": {
                "start": {
                  "line": 2,
                  "column": 7
                },
                "end": {
                  "line": 2,
                  "column": 23
                },
                "identifierName": "ASCIIDecodeError"
              },
              "name": "ASCIIDecodeError"
            }
          }
        ],
        "source": {
          "type": "StringLiteral",
          "start": 69,
          "end": 92,
          "loc": {
            "start": {
              "line": 2,
              "column": 29
            },
            "end": {
              "line": 2,
              "column": 52
            }
          },
          "extra": {
            "rawValue": "./ASCIIDecodeError.js",
            "raw": "'./ASCIIDecodeError.js'"
          },
          "value": "./ASCIIDecodeError.js"
        }
      },
      {
        "type": "ExportDefaultDeclaration",
        "start": 95,
        "end": 457,
        "loc": {
          "start": {
            "line": 4,
            "column": 0
          },
          "end": {
            "line": 19,
            "column": 1
          }
        },
        "declaration": {
          "type": "FunctionDeclaration",
          "start": 110,
          "end": 457,
          "loc": {
            "start": {
              "line": 4,
              "column": 15
            },
            "end": {
              "line": 19,
              "column": 1
            }
          },
          "id": {
            "type": "Identifier",
            "start": 120,
            "end": 127,
            "loc": {
              "start": {
                "line": 4,
                "column": 25
              },
              "end": {
                "line": 4,
                "column": 32
              },
              "identifierName": "_decode"
            },
            "name": "_decode"
          },
          "generator": true,
          "expression": false,
          "async": false,
          "params": [
            {
              "type": "Identifier",
              "start": 128,
              "end": 133,
              "loc": {
                "start": {
                  "line": 4,
                  "column": 33
                },
                "end": {
                  "line": 4,
                  "column": 38
                },
                "identifierName": "bytes"
              },
              "name": "bytes"
            },
            {
              "type": "AssignmentPattern",
              "start": 135,
              "end": 150,
              "loc": {
                "start": {
                  "line": 4,
                  "column": 40
                },
                "end": {
                  "line": 4,
                  "column": 55
                }
              },
              "left": {
                "type": "Identifier",
                "start": 135,
                "end": 143,
                "loc": {
                  "start": {
                    "line": 4,
                    "column": 40
                  },
                  "end": {
                    "line": 4,
                    "column": 48
                  },
                  "identifierName": "_options"
                },
                "name": "_options"
              },
              "right": {
                "type": "NullLiteral",
                "start": 146,
                "end": 150,
                "loc": {
                  "start": {
                    "line": 4,
                    "column": 51
                  },
                  "end": {
                    "line": 4,
                    "column": 55
                  }
                }
              }
            }
          ],
          "body": {
            "type": "BlockStatement",
            "start": 152,
            "end": 457,
            "loc": {
              "start": {
                "line": 4,
                "column": 57
              },
              "end": {
                "line": 19,
                "column": 1
              }
            },
            "body": [
              {
                "type": "VariableDeclaration",
                "start": 155,
                "end": 169,
                "loc": {
                  "start": {
                    "line": 5,
                    "column": 1
                  },
                  "end": {
                    "line": 5,
                    "column": 15
                  }
                },
                "declarations": [
                  {
                    "type": "VariableDeclarator",
                    "start": 159,
                    "end": 168,
                    "loc": {
                      "start": {
                        "line": 5,
                        "column": 5
                      },
                      "end": {
                        "line": 5,
                        "column": 14
                      }
                    },
                    "id": {
                      "type": "Identifier",
                      "start": 159,
                      "end": 164,
                      "loc": {
                        "start": {
                          "line": 5,
                          "column": 5
                        },
                        "end": {
                          "line": 5,
                          "column": 10
                        },
                        "identifierName": "start"
                      },
                      "name": "start"
                    },
                    "init": {
                      "type": "NumericLiteral",
                      "start": 167,
                      "end": 168,
                      "loc": {
                        "start": {
                          "line": 5,
                          "column": 13
                        },
                        "end": {
                          "line": 5,
                          "column": 14
                        }
                      },
                      "extra": {
                        "rawValue": 0,
                        "raw": "0"
                      },
                      "value": 0
                    }
                  }
                ],
                "kind": "let"
              },
              {
                "type": "ForOfStatement",
                "start": 172,
                "end": 455,
                "loc": {
                  "start": {
                    "line": 7,
                    "column": 1
                  },
                  "end": {
                    "line": 18,
                    "column": 2
                  }
                },
                "left": {
                  "type": "VariableDeclaration",
                  "start": 177,
                  "end": 184,
                  "loc": {
                    "start": {
                      "line": 7,
                      "column": 6
                    },
                    "end": {
                      "line": 7,
                      "column": 13
                    }
                  },
                  "declarations": [
                    {
                      "type": "VariableDeclarator",
                      "start": 183,
                      "end": 184,
                      "loc": {
                        "start": {
                          "line": 7,
                          "column": 12
                        },
                        "end": {
                          "line": 7,
                          "column": 13
                        }
                      },
                      "id": {
                        "type": "Identifier",
                        "start": 183,
                        "end": 184,
                        "loc": {
                          "start": {
                            "line": 7,
                            "column": 12
                          },
                          "end": {
                            "line": 7,
                            "column": 13
                          },
                          "identifierName": "b"
                        },
                        "name": "b"
                      },
                      "init": null
                    }
                  ],
                  "kind": "const"
                },
                "right": {
                  "type": "Identifier",
                  "start": 188,
                  "end": 193,
                  "loc": {
                    "start": {
                      "line": 7,
                      "column": 17
                    },
                    "end": {
                      "line": 7,
                      "column": 22
                    },
                    "identifierName": "bytes"
                  },
                  "name": "bytes"
                },
                "body": {
                  "type": "BlockStatement",
                  "start": 195,
                  "end": 455,
                  "loc": {
                    "start": {
                      "line": 7,
                      "column": 24
                    },
                    "end": {
                      "line": 18,
                      "column": 2
                    }
                  },
                  "body": [
                    {
                      "type": "IfStatement",
                      "start": 199,
                      "end": 417,
                      "loc": {
                        "start": {
                          "line": 8,
                          "column": 2
                        },
                        "end": {
                          "line": 13,
                          "column": 3
                        }
                      },
                      "test": {
                        "type": "LogicalExpression",
                        "start": 203,
                        "end": 223,
                        "loc": {
                          "start": {
                            "line": 8,
                            "column": 6
                          },
                          "end": {
                            "line": 8,
                            "column": 26
                          }
                        },
                        "left": {
                          "type": "BinaryExpression",
                          "start": 203,
                          "end": 211,
                          "loc": {
                            "start": {
                              "line": 8,
                              "column": 6
                            },
                            "end": {
                              "line": 8,
                              "column": 14
                            }
                          },
                          "left": {
                            "type": "Identifier",
                            "start": 203,
                            "end": 204,
                            "loc": {
                              "start": {
                                "line": 8,
                                "column": 6
                              },
                              "end": {
                                "line": 8,
                                "column": 7
                              },
                              "identifierName": "b"
                            },
                            "name": "b"
                          },
                          "operator": "<",
                          "right": {
                            "type": "NumericLiteral",
                            "start": 207,
                            "end": 211,
                            "loc": {
                              "start": {
                                "line": 8,
                                "column": 10
                              },
                              "end": {
                                "line": 8,
                                "column": 14
                              }
                            },
                            "extra": {
                              "rawValue": 0,
                              "raw": "0x00"
                            },
                            "value": 0
                          }
                        },
                        "operator": "||",
                        "right": {
                          "type": "BinaryExpression",
                          "start": 215,
                          "end": 223,
                          "loc": {
                            "start": {
                              "line": 8,
                              "column": 18
                            },
                            "end": {
                              "line": 8,
                              "column": 26
                            }
                          },
                          "left": {
                            "type": "Identifier",
                            "start": 215,
                            "end": 216,
                            "loc": {
                              "start": {
                                "line": 8,
                                "column": 18
                              },
                              "end": {
                                "line": 8,
                                "column": 19
                              },
                              "identifierName": "b"
                            },
                            "name": "b"
                          },
                          "operator": ">",
                          "right": {
                            "type": "NumericLiteral",
                            "start": 219,
                            "end": 223,
                            "loc": {
                              "start": {
                                "line": 8,
                                "column": 22
                              },
                              "end": {
                                "line": 8,
                                "column": 26
                              }
                            },
                            "extra": {
                              "rawValue": 127,
                              "raw": "0x7f"
                            },
                            "value": 127
                          }
                        }
                      },
                      "consequent": {
                        "type": "BlockStatement",
                        "start": 225,
                        "end": 417,
                        "loc": {
                          "start": {
                            "line": 8,
                            "column": 28
                          },
                          "end": {
                            "line": 13,
                            "column": 3
                          }
                        },
                        "body": [
                          {
                            "type": "VariableDeclaration",
                            "start": 230,
                            "end": 286,
                            "loc": {
                              "start": {
                                "line": 9,
                                "column": 3
                              },
                              "end": {
                                "line": 9,
                                "column": 59
                              }
                            },
                            "declarations": [
                              {
                                "type": "VariableDeclarator",
                                "start": 236,
                                "end": 285,
                                "loc": {
                                  "start": {
                                    "line": 9,
                                    "column": 9
                                  },
                                  "end": {
                                    "line": 9,
                                    "column": 58
                                  }
                                },
                                "id": {
                                  "type": "Identifier",
                                  "start": 236,
                                  "end": 242,
                                  "loc": {
                                    "start": {
                                      "line": 9,
                                      "column": 9
                                    },
                                    "end": {
                                      "line": 9,
                                      "column": 15
                                    },
                                    "identifierName": "reason"
                                  },
                                  "name": "reason"
                                },
                                "init": {
                                  "type": "TemplateLiteral",
                                  "start": 245,
                                  "end": 285,
                                  "loc": {
                                    "start": {
                                      "line": 9,
                                      "column": 18
                                    },
                                    "end": {
                                      "line": 9,
                                      "column": 58
                                    }
                                  },
                                  "expressions": [
                                    {
                                      "type": "Identifier",
                                      "start": 274,
                                      "end": 275,
                                      "loc": {
                                        "start": {
                                          "line": 9,
                                          "column": 47
                                        },
                                        "end": {
                                          "line": 9,
                                          "column": 48
                                        },
                                        "identifierName": "b"
                                      },
                                      "name": "b"
                                    }
                                  ],
                                  "quasis": [
                                    {
                                      "type": "TemplateElement",
                                      "start": 246,
                                      "end": 272,
                                      "loc": {
                                        "start": {
                                          "line": 9,
                                          "column": 19
                                        },
                                        "end": {
                                          "line": 9,
                                          "column": 45
                                        }
                                      },
                                      "value": {
                                        "raw": "byte out of range 0x00 <= ",
                                        "cooked": "byte out of range 0x00 <= "
                                      },
                                      "tail": false
                                    },
                                    {
                                      "type": "TemplateElement",
                                      "start": 276,
                                      "end": 284,
                                      "loc": {
                                        "start": {
                                          "line": 9,
                                          "column": 49
                                        },
                                        "end": {
                                          "line": 9,
                                          "column": 57
                                        }
                                      },
                                      "value": {
                                        "raw": " <= 0x7F",
                                        "cooked": " <= 0x7F"
                                      },
                                      "tail": true
                                    }
                                  ]
                                }
                              }
                            ],
                            "kind": "const"
                          },
                          {
                            "type": "VariableDeclaration",
                            "start": 290,
                            "end": 311,
                            "loc": {
                              "start": {
                                "line": 10,
                                "column": 3
                              },
                              "end": {
                                "line": 10,
                                "column": 24
                              }
                            },
                            "declarations": [
                              {
                                "type": "VariableDeclarator",
                                "start": 296,
                                "end": 310,
                                "loc": {
                                  "start": {
                                    "line": 10,
                                    "column": 9
                                  },
                                  "end": {
                                    "line": 10,
                                    "column": 23
                                  }
                                },
                                "id": {
                                  "type": "Identifier",
                                  "start": 296,
                                  "end": 302,
                                  "loc": {
                                    "start": {
                                      "line": 10,
                                      "column": 9
                                    },
                                    "end": {
                                      "line": 10,
                                      "column": 15
                                    },
                                    "identifierName": "object"
                                  },
                                  "name": "object"
                                },
                                "init": {
                                  "type": "Identifier",
                                  "start": 305,
                                  "end": 310,
                                  "loc": {
                                    "start": {
                                      "line": 10,
                                      "column": 18
                                    },
                                    "end": {
                                      "line": 10,
                                      "column": 23
                                    },
                                    "identifierName": "bytes"
                                  },
                                  "name": "bytes"
                                }
                              }
                            ],
                            "kind": "const"
                          },
                          {
                            "type": "VariableDeclaration",
                            "start": 315,
                            "end": 356,
                            "loc": {
                              "start": {
                                "line": 11,
                                "column": 3
                              },
                              "end": {
                                "line": 11,
                                "column": 44
                              }
                            },
                            "declarations": [
                              {
                                "type": "VariableDeclarator",
                                "start": 321,
                                "end": 355,
                                "loc": {
                                  "start": {
                                    "line": 11,
                                    "column": 9
                                  },
                                  "end": {
                                    "line": 11,
                                    "column": 43
                                  }
                                },
                                "id": {
                                  "type": "Identifier",
                                  "start": 321,
                                  "end": 329,
                                  "loc": {
                                    "start": {
                                      "line": 11,
                                      "column": 9
                                    },
                                    "end": {
                                      "line": 11,
                                      "column": 17
                                    },
                                    "identifierName": "position"
                                  },
                                  "name": "position"
                                },
                                "init": {
                                  "type": "ObjectExpression",
                                  "start": 332,
                                  "end": 355,
                                  "loc": {
                                    "start": {
                                      "line": 11,
                                      "column": 20
                                    },
                                    "end": {
                                      "line": 11,
                                      "column": 43
                                    }
                                  },
                                  "properties": [
                                    {
                                      "type": "ObjectProperty",
                                      "start": 333,
                                      "end": 338,
                                      "loc": {
                                        "start": {
                                          "line": 11,
                                          "column": 21
                                        },
                                        "end": {
                                          "line": 11,
                                          "column": 26
                                        }
                                      },
                                      "method": false,
                                      "shorthand": true,
                                      "computed": false,
                                      "key": {
                                        "type": "Identifier",
                                        "start": 333,
                                        "end": 338,
                                        "loc": {
                                          "start": {
                                            "line": 11,
                                            "column": 21
                                          },
                                          "end": {
                                            "line": 11,
                                            "column": 26
                                          },
                                          "identifierName": "start"
                                        },
                                        "name": "start"
                                      },
                                      "value": {
                                        "type": "Identifier",
                                        "start": 333,
                                        "end": 338,
                                        "loc": {
                                          "start": {
                                            "line": 11,
                                            "column": 21
                                          },
                                          "end": {
                                            "line": 11,
                                            "column": 26
                                          },
                                          "identifierName": "start"
                                        },
                                        "name": "start"
                                      },
                                      "extra": {
                                        "shorthand": true
                                      }
                                    },
                                    {
                                      "type": "ObjectProperty",
                                      "start": 340,
                                      "end": 354,
                                      "loc": {
                                        "start": {
                                          "line": 11,
                                          "column": 28
                                        },
                                        "end": {
                                          "line": 11,
                                          "column": 42
                                        }
                                      },
                                      "method": false,
                                      "shorthand": false,
                                      "computed": false,
                                      "key": {
                                        "type": "Identifier",
                                        "start": 340,
                                        "end": 343,
                                        "loc": {
                                          "start": {
                                            "line": 11,
                                            "column": 28
                                          },
                                          "end": {
                                            "line": 11,
                                            "column": 31
                                          },
                                          "identifierName": "end"
                                        },
                                        "name": "end"
                                      },
                                      "value": {
                                        "type": "BinaryExpression",
                                        "start": 345,
                                        "end": 354,
                                        "loc": {
                                          "start": {
                                            "line": 11,
                                            "column": 33
                                          },
                                          "end": {
                                            "line": 11,
                                            "column": 42
                                          }
                                        },
                                        "left": {
                                          "type": "Identifier",
                                          "start": 345,
                                          "end": 350,
                                          "loc": {
                                            "start": {
                                              "line": 11,
                                              "column": 33
                                            },
                                            "end": {
                                              "line": 11,
                                              "column": 38
                                            },
                                            "identifierName": "start"
                                          },
                                          "name": "start"
                                        },
                                        "operator": "+",
                                        "right": {
                                          "type": "NumericLiteral",
                                          "start": 353,
                                          "end": 354,
                                          "loc": {
                                            "start": {
                                              "line": 11,
                                              "column": 41
                                            },
                                            "end": {
                                              "line": 11,
                                              "column": 42
                                            }
                                          },
                                          "extra": {
                                            "rawValue": 1,
                                            "raw": "1"
                                          },
                                          "value": 1
                                        }
                                      }
                                    }
                                  ]
                                }
                              }
                            ],
                            "kind": "const"
                          },
                          {
                            "type": "ThrowStatement",
                            "start": 360,
                            "end": 413,
                            "loc": {
                              "start": {
                                "line": 12,
                                "column": 3
                              },
                              "end": {
                                "line": 12,
                                "column": 56
                              }
                            },
                            "argument": {
                              "type": "NewExpression",
                              "start": 366,
                              "end": 412,
                              "loc": {
                                "start": {
                                  "line": 12,
                                  "column": 9
                                },
                                "end": {
                                  "line": 12,
                                  "column": 55
                                }
                              },
                              "callee": {
                                "type": "Identifier",
                                "start": 370,
                                "end": 386,
                                "loc": {
                                  "start": {
                                    "line": 12,
                                    "column": 13
                                  },
                                  "end": {
                                    "line": 12,
                                    "column": 29
                                  },
                                  "identifierName": "ASCIIDecodeError"
                                },
                                "name": "ASCIIDecodeError"
                              },
                              "arguments": [
                                {
                                  "type": "Identifier",
                                  "start": 387,
                                  "end": 393,
                                  "loc": {
                                    "start": {
                                      "line": 12,
                                      "column": 30
                                    },
                                    "end": {
                                      "line": 12,
                                      "column": 36
                                    },
                                    "identifierName": "reason"
                                  },
                                  "name": "reason"
                                },
                                {
                                  "type": "Identifier",
                                  "start": 395,
                                  "end": 401,
                                  "loc": {
                                    "start": {
                                      "line": 12,
                                      "column": 38
                                    },
                                    "end": {
                                      "line": 12,
                                      "column": 44
                                    },
                                    "identifierName": "object"
                                  },
                                  "name": "object"
                                },
                                {
                                  "type": "Identifier",
                                  "start": 403,
                                  "end": 411,
                                  "loc": {
                                    "start": {
                                      "line": 12,
                                      "column": 46
                                    },
                                    "end": {
                                      "line": 12,
                                      "column": 54
                                    },
                                    "identifierName": "position"
                                  },
                                  "name": "position"
                                }
                              ]
                            }
                          }
                        ],
                        "directives": []
                      },
                      "alternate": null
                    },
                    {
                      "type": "ExpressionStatement",
                      "start": 421,
                      "end": 440,
                      "loc": {
                        "start": {
                          "line": 15,
                          "column": 2
                        },
                        "end": {
                          "line": 15,
                          "column": 21
                        }
                      },
                      "expression": {
                        "type": "YieldExpression",
                        "start": 421,
                        "end": 439,
                        "loc": {
                          "start": {
                            "line": 15,
                            "column": 2
                          },
                          "end": {
                            "line": 15,
                            "column": 20
                          }
                        },
                        "delegate": false,
                        "argument": {
                          "type": "MemberExpression",
                          "start": 427,
                          "end": 439,
                          "loc": {
                            "start": {
                              "line": 15,
                              "column": 8
                            },
                            "end": {
                              "line": 15,
                              "column": 20
                            }
                          },
                          "object": {
                            "type": "Identifier",
                            "start": 427,
                            "end": 436,
                            "loc": {
                              "start": {
                                "line": 15,
                                "column": 8
                              },
                              "end": {
                                "line": 15,
                                "column": 17
                              },
                              "identifierName": "byte2char"
                            },
                            "name": "byte2char"
                          },
                          "property": {
                            "type": "Identifier",
                            "start": 437,
                            "end": 438,
                            "loc": {
                              "start": {
                                "line": 15,
                                "column": 18
                              },
                              "end": {
                                "line": 15,
                                "column": 19
                              },
                              "identifierName": "b"
                            },
                            "name": "b"
                          },
                          "computed": true
                        }
                      }
                    },
                    {
                      "type": "ExpressionStatement",
                      "start": 444,
                      "end": 452,
                      "loc": {
                        "start": {
                          "line": 17,
                          "column": 2
                        },
                        "end": {
                          "line": 17,
                          "column": 10
                        }
                      },
                      "expression": {
                        "type": "UpdateExpression",
                        "start": 444,
                        "end": 451,
                        "loc": {
                          "start": {
                            "line": 17,
                            "column": 2
                          },
                          "end": {
                            "line": 17,
                            "column": 9
                          }
                        },
                        "operator": "++",
                        "prefix": true,
                        "argument": {
                          "type": "Identifier",
                          "start": 446,
                          "end": 451,
                          "loc": {
                            "start": {
                              "line": 17,
                              "column": 4
                            },
                            "end": {
                              "line": 17,
                              "column": 9
                            },
                            "identifierName": "start"
                          },
                          "name": "start"
                        },
                        "extra": {
                          "parenthesizedArgument": false
                        }
                      }
                    }
                  ],
                  "directives": []
                }
              }
            ],
            "directives": []
          },
          "leadingComments": [],
          "trailingComments": []
        }
      }
    ],
    "directives": []
  },
  "comments": [],
  "tokens": [
    {
      "type": {
        "label": "import",
        "keyword": "import",
        "beforeExpr": false,
        "startsExpr": true,
        "rightAssociative": false,
        "isLoop": false,
        "isAssign": false,
        "prefix": false,
        "postfix": false,
        "binop": null,
        "updateContext": null
      },
      "value": "import",
      "start": 0,
      "end": 6,
      "loc": {
        "start": {
          "line": 1,
          "column": 0
        },
        "end": {
          "line": 1,
          "column": 6
        }
      }
    },
    {
      "type": {
        "label": "name",
        "beforeExpr": false,
        "startsExpr": true,
        "rightAssociative": false,
        "isLoop": false,
        "isAssign": false,
        "prefix": false,
        "postfix": false,
        "binop": null
      },
      "value": "byte2char",
      "start": 7,
      "end": 16,
      "loc": {
        "start": {
          "line": 1,
          "column": 7
        },
        "end": {
          "line": 1,
          "column": 16
        }
      }
    },
    {
      "type": {
        "label": "name",
        "beforeExpr": false,
        "startsExpr": true,
        "rightAssociative": false,
        "isLoop": false,
        "isAssign": false,
        "prefix": false,
        "postfix": false,
        "binop": null
      },
      "value": "from",
      "start": 17,
      "end": 21,
      "loc": {
        "start": {
          "line": 1,
          "column": 17
        },
        "end": {
          "line": 1,
          "column": 21
        }
      }
    },
    {
      "type": {
        "label": "string",
        "beforeExpr": false,
        "startsExpr": true,
        "rightAssociative": false,
        "isLoop": false,
        "isAssign": false,
        "prefix": false,
        "postfix": false,
        "binop": null,
        "updateContext": null
      },
      "value": "./byte2char.js",
      "start": 22,
      "end": 38,
      "loc": {
        "start": {
          "line": 1,
          "column": 22
        },
        "end": {
          "line": 1,
          "column": 38
        }
      }
    },
    {
      "type": {
        "label": ";",
        "beforeExpr": true,
        "startsExpr": false,
        "rightAssociative": false,
        "isLoop": false,
        "isAssign": false,
        "prefix": false,
        "postfix": false,
        "binop": null,
        "updateContext": null
      },
      "start": 38,
      "end": 39,
      "loc": {
        "start": {
          "line": 1,
          "column": 38
        },
        "end": {
          "line": 1,
          "column": 39
        }
      }
    },
    {
      "type": {
        "label": "import",
        "keyword": "import",
        "beforeExpr": false,
        "startsExpr": true,
        "rightAssociative": false,
        "isLoop": false,
        "isAssign": false,
        "prefix": false,
        "postfix": false,
        "binop": null,
        "updateContext": null
      },
      "value": "import",
      "start": 40,
      "end": 46,
      "loc": {
        "start": {
          "line": 2,
          "column": 0
        },
        "end": {
          "line": 2,
          "column": 6
        }
      }
    },
    {
      "type": {
        "label": "name",
        "beforeExpr": false,
        "startsExpr": true,
        "rightAssociative": false,
        "isLoop": false,
        "isAssign": false,
        "prefix": false,
        "postfix": false,
        "binop": null
      },
      "value": "ASCIIDecodeError",
      "start": 47,
      "end": 63,
      "loc": {
        "start": {
          "line": 2,
          "column": 7
        },
        "end": {
          "line": 2,
          "column": 23
        }
      }
    },
    {
      "type": {
        "label": "name",
        "beforeExpr": false,
        "startsExpr": true,
        "rightAssociative": false,
        "isLoop": false,
        "isAssign": false,
        "prefix": false,
        "postfix": false,
        "binop": null
      },
      "value": "from",
      "start": 64,
      "end": 68,
      "loc": {
        "start": {
          "line": 2,
          "column": 24
        },
        "end": {
          "line": 2,
          "column": 28
        }
      }
    },
    {
      "type": {
        "label": "string",
        "beforeExpr": false,
        "startsExpr": true,
        "rightAssociative": false,
        "isLoop": false,
        "isAssign": false,
        "prefix": false,
        "postfix": false,
        "binop": null,
        "updateContext": null
      },
      "value": "./ASCIIDecodeError.js",
      "start": 69,
      "end": 92,
      "loc": {
        "start": {
          "line": 2,
          "column": 29
        },
        "end": {
          "line": 2,
          "column": 52
        }
      }
    },
    {
      "type": {
        "label": ";",
        "beforeExpr": true,
        "startsExpr": false,
        "rightAssociative": false,
        "isLoop": false,
        "isAssign": false,
        "prefix": false,
        "postfix": false,
        "binop": null,
        "updateContext": null
      },
      "start": 92,
      "end": 93,
      "loc": {
        "start": {
          "line": 2,
          "column": 52
        },
        "end": {
          "line": 2,
          "column": 53
        }
      }
    },
    {
      "type": {
        "label": "export",
        "keyword": "export",
        "beforeExpr": false,
        "startsExpr": false,
        "rightAssociative": false,
        "isLoop": false,
        "isAssign": false,
        "prefix": false,
        "postfix": false,
        "binop": null,
        "updateContext": null
      },
      "value": "export",
      "start": 95,
      "end": 101,
      "loc": {
        "start": {
          "line": 4,
          "column": 0
        },
        "end": {
          "line": 4,
          "column": 6
        }
      }
    },
    {
      "type": {
        "label": "default",
        "keyword": "default",
        "beforeExpr": true,
        "startsExpr": false,
        "rightAssociative": false,
        "isLoop": false,
        "isAssign": false,
        "prefix": false,
        "postfix": false,
        "binop": null,
        "updateContext": null
      },
      "value": "default",
      "start": 102,
      "end": 109,
      "loc": {
        "start": {
          "line": 4,
          "column": 7
        },
        "end": {
          "line": 4,
          "column": 14
        }
      }
    },
    {
      "type": {
        "label": "function",
        "keyword": "function",
        "beforeExpr": false,
        "startsExpr": true,
        "rightAssociative": false,
        "isLoop": false,
        "isAssign": false,
        "prefix": false,
        "postfix": false,
        "binop": null
      },
      "value": "function",
      "start": 110,
      "end": 118,
      "loc": {
        "start": {
          "line": 4,
          "column": 15
        },
        "end": {
          "line": 4,
          "column": 23
        }
      }
    },
    {
      "type": {
        "label": "*",
        "beforeExpr": true,
        "startsExpr": false,
        "rightAssociative": false,
        "isLoop": false,
        "isAssign": false,
        "prefix": false,
        "postfix": false,
        "binop": 10,
        "updateContext": null
      },
      "value": "*",
      "start": 118,
      "end": 119,
      "loc": {
        "start": {
          "line": 4,
          "column": 23
        },
        "end": {
          "line": 4,
          "column": 24
        }
      }
    },
    {
      "type": {
        "label": "name",
        "beforeExpr": false,
        "startsExpr": true,
        "rightAssociative": false,
        "isLoop": false,
        "isAssign": false,
        "prefix": false,
        "postfix": false,
        "binop": null
      },
      "value": "_decode",
      "start": 120,
      "end": 127,
      "loc": {
        "start": {
          "line": 4,
          "column": 25
        },
        "end": {
          "line": 4,
          "column": 32
        }
      }
    },
    {
      "type": {
        "label": "(",
        "beforeExpr": true,
        "startsExpr": true,
        "rightAssociative": false,
        "isLoop": false,
        "isAssign": false,
        "prefix": false,
        "postfix": false,
        "binop": null
      },
      "start": 127,
      "end": 128,
      "loc": {
        "start": {
          "line": 4,
          "column": 32
        },
        "end": {
          "line": 4,
          "column": 33
        }
      }
    },
    {
      "type": {
        "label": "name",
        "beforeExpr": false,
        "startsExpr": true,
        "rightAssociative": false,
        "isLoop": false,
        "isAssign": false,
        "prefix": false,
        "postfix": false,
        "binop": null
      },
      "value": "bytes",
      "start": 128,
      "end": 133,
      "loc": {
        "start": {
          "line": 4,
          "column": 33
        },
        "end": {
          "line": 4,
          "column": 38
        }
      }
    },
    {
      "type": {
        "label": ",",
        "beforeExpr": true,
        "startsExpr": false,
        "rightAssociative": false,
        "isLoop": false,
        "isAssign": false,
        "prefix": false,
        "postfix": false,
        "binop": null,
        "updateContext": null
      },
      "start": 133,
      "end": 134,
      "loc": {
        "start": {
          "line": 4,
          "column": 38
        },
        "end": {
          "line": 4,
          "column": 39
        }
      }
    },
    {
      "type": {
        "label": "name",
        "beforeExpr": false,
        "startsExpr": true,
        "rightAssociative": false,
        "isLoop": false,
        "isAssign": false,
        "prefix": false,
        "postfix": false,
        "binop": null
      },
      "value": "_options",
      "start": 135,
      "end": 143,
      "loc": {
        "start": {
          "line": 4,
          "column": 40
        },
        "end": {
          "line": 4,
          "column": 48
        }
      }
    },
    {
      "type": {
        "label": "=",
        "beforeExpr": true,
        "startsExpr": false,
        "rightAssociative": false,
        "isLoop": false,
        "isAssign": true,
        "prefix": false,
        "postfix": false,
        "binop": null,
        "updateContext": null
      },
      "value": "=",
      "start": 144,
      "end": 145,
      "loc": {
        "start": {
          "line": 4,
          "column": 49
        },
        "end": {
          "line": 4,
          "column": 50
        }
      }
    },
    {
      "type": {
        "label": "null",
        "keyword": "null",
        "beforeExpr": false,
        "startsExpr": true,
        "rightAssociative": false,
        "isLoop": false,
        "isAssign": false,
        "prefix": false,
        "postfix": false,
        "binop": null,
        "updateContext": null
      },
      "value": "null",
      "start": 146,
      "end": 150,
      "loc": {
        "start": {
          "line": 4,
          "column": 51
        },
        "end": {
          "line": 4,
          "column": 55
        }
      }
    },
    {
      "type": {
        "label": ")",
        "beforeExpr": false,
        "startsExpr": false,
        "rightAssociative": false,
        "isLoop": false,
        "isAssign": false,
        "prefix": false,
        "postfix": false,
        "binop": null
      },
      "start": 150,
      "end": 151,
      "loc": {
        "start": {
          "line": 4,
          "column": 55
        },
        "end": {
          "line": 4,
          "column": 56
        }
      }
    },
    {
      "type": {
        "label": "{",
        "beforeExpr": true,
        "startsExpr": true,
        "rightAssociative": false,
        "isLoop": false,
        "isAssign": false,
        "prefix": false,
        "postfix": false,
        "binop": null
      },
      "start": 152,
      "end": 153,
      "loc": {
        "start": {
          "line": 4,
          "column": 57
        },
        "end": {
          "line": 4,
          "column": 58
        }
      }
    },
    {
      "type": {
        "label": "let",
        "keyword": "let",
        "beforeExpr": false,
        "startsExpr": false,
        "rightAssociative": false,
        "isLoop": false,
        "isAssign": false,
        "prefix": false,
        "postfix": false,
        "binop": null,
        "updateContext": null
      },
      "value": "let",
      "start": 155,
      "end": 158,
      "loc": {
        "start": {
          "line": 5,
          "column": 1
        },
        "end": {
          "line": 5,
          "column": 4
        }
      }
    },
    {
      "type": {
        "label": "name",
        "beforeExpr": false,
        "startsExpr": true,
        "rightAssociative": false,
        "isLoop": false,
        "isAssign": false,
        "prefix": false,
        "postfix": false,
        "binop": null
      },
      "value": "start",
      "start": 159,
      "end": 164,
      "loc": {
        "start": {
          "line": 5,
          "column": 5
        },
        "end": {
          "line": 5,
          "column": 10
        }
      }
    },
    {
      "type": {
        "label": "=",
        "beforeExpr": true,
        "startsExpr": false,
        "rightAssociative": false,
        "isLoop": false,
        "isAssign": true,
        "prefix": false,
        "postfix": false,
        "binop": null,
        "updateContext": null
      },
      "value": "=",
      "start": 165,
      "end": 166,
      "loc": {
        "start": {
          "line": 5,
          "column": 11
        },
        "end": {
          "line": 5,
          "column": 12
        }
      }
    },
    {
      "type": {
        "label": "num",
        "beforeExpr": false,
        "startsExpr": true,
        "rightAssociative": false,
        "isLoop": false,
        "isAssign": false,
        "prefix": false,
        "postfix": false,
        "binop": null,
        "updateContext": null
      },
      "value": 0,
      "start": 167,
      "end": 168,
      "loc": {
        "start": {
          "line": 5,
          "column": 13
        },
        "end": {
          "line": 5,
          "column": 14
        }
      }
    },
    {
      "type": {
        "label": ";",
        "beforeExpr": true,
        "startsExpr": false,
        "rightAssociative": false,
        "isLoop": false,
        "isAssign": false,
        "prefix": false,
        "postfix": false,
        "binop": null,
        "updateContext": null
      },
      "start": 168,
      "end": 169,
      "loc": {
        "start": {
          "line": 5,
          "column": 14
        },
        "end": {
          "line": 5,
          "column": 15
        }
      }
    },
    {
      "type": {
        "label": "for",
        "keyword": "for",
        "beforeExpr": false,
        "startsExpr": false,
        "rightAssociative": false,
        "isLoop": true,
        "isAssign": false,
        "prefix": false,
        "postfix": false,
        "binop": null,
        "updateContext": null
      },
      "value": "for",
      "start": 172,
      "end": 175,
      "loc": {
        "start": {
          "line": 7,
          "column": 1
        },
        "end": {
          "line": 7,
          "column": 4
        }
      }
    },
    {
      "type": {
        "label": "(",
        "beforeExpr": true,
        "startsExpr": true,
        "rightAssociative": false,
        "isLoop": false,
        "isAssign": false,
        "prefix": false,
        "postfix": false,
        "binop": null
      },
      "start": 176,
      "end": 177,
      "loc": {
        "start": {
          "line": 7,
          "column": 5
        },
        "end": {
          "line": 7,
          "column": 6
        }
      }
    },
    {
      "type": {
        "label": "const",
        "keyword": "const",
        "beforeExpr": false,
        "startsExpr": false,
        "rightAssociative": false,
        "isLoop": false,
        "isAssign": false,
        "prefix": false,
        "postfix": false,
        "binop": null,
        "updateContext": null
      },
      "value": "const",
      "start": 177,
      "end": 182,
      "loc": {
        "start": {
          "line": 7,
          "column": 6
        },
        "end": {
          "line": 7,
          "column": 11
        }
      }
    },
    {
      "type": {
        "label": "name",
        "beforeExpr": false,
        "startsExpr": true,
        "rightAssociative": false,
        "isLoop": false,
        "isAssign": false,
        "prefix": false,
        "postfix": false,
        "binop": null
      },
      "value": "b",
      "start": 183,
      "end": 184,
      "loc": {
        "start": {
          "line": 7,
          "column": 12
        },
        "end": {
          "line": 7,
          "column": 13
        }
      }
    },
    {
      "type": {
        "label": "name",
        "beforeExpr": false,
        "startsExpr": true,
        "rightAssociative": false,
        "isLoop": false,
        "isAssign": false,
        "prefix": false,
        "postfix": false,
        "binop": null
      },
      "value": "of",
      "start": 185,
      "end": 187,
      "loc": {
        "start": {
          "line": 7,
          "column": 14
        },
        "end": {
          "line": 7,
          "column": 16
        }
      }
    },
    {
      "type": {
        "label": "name",
        "beforeExpr": false,
        "startsExpr": true,
        "rightAssociative": false,
        "isLoop": false,
        "isAssign": false,
        "prefix": false,
        "postfix": false,
        "binop": null
      },
      "value": "bytes",
      "start": 188,
      "end": 193,
      "loc": {
        "start": {
          "line": 7,
          "column": 17
        },
        "end": {
          "line": 7,
          "column": 22
        }
      }
    },
    {
      "type": {
        "label": ")",
        "beforeExpr": false,
        "startsExpr": false,
        "rightAssociative": false,
        "isLoop": false,
        "isAssign": false,
        "prefix": false,
        "postfix": false,
        "binop": null
      },
      "start": 193,
      "end": 194,
      "loc": {
        "start": {
          "line": 7,
          "column": 22
        },
        "end": {
          "line": 7,
          "column": 23
        }
      }
    },
    {
      "type": {
        "label": "{",
        "beforeExpr": true,
        "startsExpr": true,
        "rightAssociative": false,
        "isLoop": false,
        "isAssign": false,
        "prefix": false,
        "postfix": false,
        "binop": null
      },
      "start": 195,
      "end": 196,
      "loc": {
        "start": {
          "line": 7,
          "column": 24
        },
        "end": {
          "line": 7,
          "column": 25
        }
      }
    },
    {
      "type": {
        "label": "if",
        "keyword": "if",
        "beforeExpr": false,
        "startsExpr": false,
        "rightAssociative": false,
        "isLoop": false,
        "isAssign": false,
        "prefix": false,
        "postfix": false,
        "binop": null,
        "updateContext": null
      },
      "value": "if",
      "start": 199,
      "end": 201,
      "loc": {
        "start": {
          "line": 8,
          "column": 2
        },
        "end": {
          "line": 8,
          "column": 4
        }
      }
    },
    {
      "type": {
        "label": "(",
        "beforeExpr": true,
        "startsExpr": true,
        "rightAssociative": false,
        "isLoop": false,
        "isAssign": false,
        "prefix": false,
        "postfix": false,
        "binop": null
      },
      "start": 202,
      "end": 203,
      "loc": {
        "start": {
          "line": 8,
          "column": 5
        },
        "end": {
          "line": 8,
          "column": 6
        }
      }
    },
    {
      "type": {
        "label": "name",
        "beforeExpr": false,
        "startsExpr": true,
        "rightAssociative": false,
        "isLoop": false,
        "isAssign": false,
        "prefix": false,
        "postfix": false,
        "binop": null
      },
      "value": "b",
      "start": 203,
      "end": 204,
      "loc": {
        "start": {
          "line": 8,
          "column": 6
        },
        "end": {
          "line": 8,
          "column": 7
        }
      }
    },
    {
      "type": {
        "label": "</>",
        "beforeExpr": true,
        "startsExpr": false,
        "rightAssociative": false,
        "isLoop": false,
        "isAssign": false,
        "prefix": false,
        "postfix": false,
        "binop": 7,
        "updateContext": null
      },
      "value": "<",
      "start": 205,
      "end": 206,
      "loc": {
        "start": {
          "line": 8,
          "column": 8
        },
        "end": {
          "line": 8,
          "column": 9
        }
      }
    },
    {
      "type": {
        "label": "num",
        "beforeExpr": false,
        "startsExpr": true,
        "rightAssociative": false,
        "isLoop": false,
        "isAssign": false,
        "prefix": false,
        "postfix": false,
        "binop": null,
        "updateContext": null
      },
      "value": 0,
      "start": 207,
      "end": 211,
      "loc": {
        "start": {
          "line": 8,
          "column": 10
        },
        "end": {
          "line": 8,
          "column": 14
        }
      }
    },
    {
      "type": {
        "label": "||",
        "beforeExpr": true,
        "startsExpr": false,
        "rightAssociative": false,
        "isLoop": false,
        "isAssign": false,
        "prefix": false,
        "postfix": false,
        "binop": 1,
        "updateContext": null
      },
      "value": "||",
      "start": 212,
      "end": 214,
      "loc": {
        "start": {
          "line": 8,
          "column": 15
        },
        "end": {
          "line": 8,
          "column": 17
        }
      }
    },
    {
      "type": {
        "label": "name",
        "beforeExpr": false,
        "startsExpr": true,
        "rightAssociative": false,
        "isLoop": false,
        "isAssign": false,
        "prefix": false,
        "postfix": false,
        "binop": null
      },
      "value": "b",
      "start": 215,
      "end": 216,
      "loc": {
        "start": {
          "line": 8,
          "column": 18
        },
        "end": {
          "line": 8,
          "column": 19
        }
      }
    },
    {
      "type": {
        "label": "</>",
        "beforeExpr": true,
        "startsExpr": false,
        "rightAssociative": false,
        "isLoop": false,
        "isAssign": false,
        "prefix": false,
        "postfix": false,
        "binop": 7,
        "updateContext": null
      },
      "value": ">",
      "start": 217,
      "end": 218,
      "loc": {
        "start": {
          "line": 8,
          "column": 20
        },
        "end": {
          "line": 8,
          "column": 21
        }
      }
    },
    {
      "type": {
        "label": "num",
        "beforeExpr": false,
        "startsExpr": true,
        "rightAssociative": false,
        "isLoop": false,
        "isAssign": false,
        "prefix": false,
        "postfix": false,
        "binop": null,
        "updateContext": null
      },
      "value": 127,
      "start": 219,
      "end": 223,
      "loc": {
        "start": {
          "line": 8,
          "column": 22
        },
        "end": {
          "line": 8,
          "column": 26
        }
      }
    },
    {
      "type": {
        "label": ")",
        "beforeExpr": false,
        "startsExpr": false,
        "rightAssociative": false,
        "isLoop": false,
        "isAssign": false,
        "prefix": false,
        "postfix": false,
        "binop": null
      },
      "start": 223,
      "end": 224,
      "loc": {
        "start": {
          "line": 8,
          "column": 26
        },
        "end": {
          "line": 8,
          "column": 27
        }
      }
    },
    {
      "type": {
        "label": "{",
        "beforeExpr": true,
        "startsExpr": true,
        "rightAssociative": false,
        "isLoop": false,
        "isAssign": false,
        "prefix": false,
        "postfix": false,
        "binop": null
      },
      "start": 225,
      "end": 226,
      "loc": {
        "start": {
          "line": 8,
          "column": 28
        },
        "end": {
          "line": 8,
          "column": 29
        }
      }
    },
    {
      "type": {
        "label": "const",
        "keyword": "const",
        "beforeExpr": false,
        "startsExpr": false,
        "rightAssociative": false,
        "isLoop": false,
        "isAssign": false,
        "prefix": false,
        "postfix": false,
        "binop": null,
        "updateContext": null
      },
      "value": "const",
      "start": 230,
      "end": 235,
      "loc": {
        "start": {
          "line": 9,
          "column": 3
        },
        "end": {
          "line": 9,
          "column": 8
        }
      }
    },
    {
      "type": {
        "label": "name",
        "beforeExpr": false,
        "startsExpr": true,
        "rightAssociative": false,
        "isLoop": false,
        "isAssign": false,
        "prefix": false,
        "postfix": false,
        "binop": null
      },
      "value": "reason",
      "start": 236,
      "end": 242,
      "loc": {
        "start": {
          "line": 9,
          "column": 9
        },
        "end": {
          "line": 9,
          "column": 15
        }
      }
    },
    {
      "type": {
        "label": "=",
        "beforeExpr": true,
        "startsExpr": false,
        "rightAssociative": false,
        "isLoop": false,
        "isAssign": true,
        "prefix": false,
        "postfix": false,
        "binop": null,
        "updateContext": null
      },
      "value": "=",
      "start": 243,
      "end": 244,
      "loc": {
        "start": {
          "line": 9,
          "column": 16
        },
        "end": {
          "line": 9,
          "column": 17
        }
      }
    },
    {
      "type": {
        "label": "`",
        "beforeExpr": false,
        "startsExpr": true,
        "rightAssociative": false,
        "isLoop": false,
        "isAssign": false,
        "prefix": false,
        "postfix": false,
        "binop": null
      },
      "start": 245,
      "end": 246,
      "loc": {
        "start": {
          "line": 9,
          "column": 18
        },
        "end": {
          "line": 9,
          "column": 19
        }
      }
    },
    {
      "type": {
        "label": "template",
        "beforeExpr": false,
        "startsExpr": false,
        "rightAssociative": false,
        "isLoop": false,
        "isAssign": false,
        "prefix": false,
        "postfix": false,
        "binop": null,
        "updateContext": null
      },
      "value": "byte out of range 0x00 <= ",
      "start": 246,
      "end": 272,
      "loc": {
        "start": {
          "line": 9,
          "column": 19
        },
        "end": {
          "line": 9,
          "column": 45
        }
      }
    },
    {
      "type": {
        "label": "${",
        "beforeExpr": true,
        "startsExpr": true,
        "rightAssociative": false,
        "isLoop": false,
        "isAssign": false,
        "prefix": false,
        "postfix": false,
        "binop": null
      },
      "start": 272,
      "end": 274,
      "loc": {
        "start": {
          "line": 9,
          "column": 45
        },
        "end": {
          "line": 9,
          "column": 47
        }
      }
    },
    {
      "type": {
        "label": "name",
        "beforeExpr": false,
        "startsExpr": true,
        "rightAssociative": false,
        "isLoop": false,
        "isAssign": false,
        "prefix": false,
        "postfix": false,
        "binop": null
      },
      "value": "b",
      "start": 274,
      "end": 275,
      "loc": {
        "start": {
          "line": 9,
          "column": 47
        },
        "end": {
          "line": 9,
          "column": 48
        }
      }
    },
    {
      "type": {
        "label": "}",
        "beforeExpr": false,
        "startsExpr": false,
        "rightAssociative": false,
        "isLoop": false,
        "isAssign": false,
        "prefix": false,
        "postfix": false,
        "binop": null
      },
      "start": 275,
      "end": 276,
      "loc": {
        "start": {
          "line": 9,
          "column": 48
        },
        "end": {
          "line": 9,
          "column": 49
        }
      }
    },
    {
      "type": {
        "label": "template",
        "beforeExpr": false,
        "startsExpr": false,
        "rightAssociative": false,
        "isLoop": false,
        "isAssign": false,
        "prefix": false,
        "postfix": false,
        "binop": null,
        "updateContext": null
      },
      "value": " <= 0x7F",
      "start": 276,
      "end": 284,
      "loc": {
        "start": {
          "line": 9,
          "column": 49
        },
        "end": {
          "line": 9,
          "column": 57
        }
      }
    },
    {
      "type": {
        "label": "`",
        "beforeExpr": false,
        "startsExpr": true,
        "rightAssociative": false,
        "isLoop": false,
        "isAssign": false,
        "prefix": false,
        "postfix": false,
        "binop": null
      },
      "start": 284,
      "end": 285,
      "loc": {
        "start": {
          "line": 9,
          "column": 57
        },
        "end": {
          "line": 9,
          "column": 58
        }
      }
    },
    {
      "type": {
        "label": ";",
        "beforeExpr": true,
        "startsExpr": false,
        "rightAssociative": false,
        "isLoop": false,
        "isAssign": false,
        "prefix": false,
        "postfix": false,
        "binop": null,
        "updateContext": null
      },
      "start": 285,
      "end": 286,
      "loc": {
        "start": {
          "line": 9,
          "column": 58
        },
        "end": {
          "line": 9,
          "column": 59
        }
      }
    },
    {
      "type": {
        "label": "const",
        "keyword": "const",
        "beforeExpr": false,
        "startsExpr": false,
        "rightAssociative": false,
        "isLoop": false,
        "isAssign": false,
        "prefix": false,
        "postfix": false,
        "binop": null,
        "updateContext": null
      },
      "value": "const",
      "start": 290,
      "end": 295,
      "loc": {
        "start": {
          "line": 10,
          "column": 3
        },
        "end": {
          "line": 10,
          "column": 8
        }
      }
    },
    {
      "type": {
        "label": "name",
        "beforeExpr": false,
        "startsExpr": true,
        "rightAssociative": false,
        "isLoop": false,
        "isAssign": false,
        "prefix": false,
        "postfix": false,
        "binop": null
      },
      "value": "object",
      "start": 296,
      "end": 302,
      "loc": {
        "start": {
          "line": 10,
          "column": 9
        },
        "end": {
          "line": 10,
          "column": 15
        }
      }
    },
    {
      "type": {
        "label": "=",
        "beforeExpr": true,
        "startsExpr": false,
        "rightAssociative": false,
        "isLoop": false,
        "isAssign": true,
        "prefix": false,
        "postfix": false,
        "binop": null,
        "updateContext": null
      },
      "value": "=",
      "start": 303,
      "end": 304,
      "loc": {
        "start": {
          "line": 10,
          "column": 16
        },
        "end": {
          "line": 10,
          "column": 17
        }
      }
    },
    {
      "type": {
        "label": "name",
        "beforeExpr": false,
        "startsExpr": true,
        "rightAssociative": false,
        "isLoop": false,
        "isAssign": false,
        "prefix": false,
        "postfix": false,
        "binop": null
      },
      "value": "bytes",
      "start": 305,
      "end": 310,
      "loc": {
        "start": {
          "line": 10,
          "column": 18
        },
        "end": {
          "line": 10,
          "column": 23
        }
      }
    },
    {
      "type": {
        "label": ";",
        "beforeExpr": true,
        "startsExpr": false,
        "rightAssociative": false,
        "isLoop": false,
        "isAssign": false,
        "prefix": false,
        "postfix": false,
        "binop": null,
        "updateContext": null
      },
      "start": 310,
      "end": 311,
      "loc": {
        "start": {
          "line": 10,
          "column": 23
        },
        "end": {
          "line": 10,
          "column": 24
        }
      }
    },
    {
      "type": {
        "label": "const",
        "keyword": "const",
        "beforeExpr": false,
        "startsExpr": false,
        "rightAssociative": false,
        "isLoop": false,
        "isAssign": false,
        "prefix": false,
        "postfix": false,
        "binop": null,
        "updateContext": null
      },
      "value": "const",
      "start": 315,
      "end": 320,
      "loc": {
        "start": {
          "line": 11,
          "column": 3
        },
        "end": {
          "line": 11,
          "column": 8
        }
      }
    },
    {
      "type": {
        "label": "name",
        "beforeExpr": false,
        "startsExpr": true,
        "rightAssociative": false,
        "isLoop": false,
        "isAssign": false,
        "prefix": false,
        "postfix": false,
        "binop": null
      },
      "value": "position",
      "start": 321,
      "end": 329,
      "loc": {
        "start": {
          "line": 11,
          "column": 9
        },
        "end": {
          "line": 11,
          "column": 17
        }
      }
    },
    {
      "type": {
        "label": "=",
        "beforeExpr": true,
        "startsExpr": false,
        "rightAssociative": false,
        "isLoop": false,
        "isAssign": true,
        "prefix": false,
        "postfix": false,
        "binop": null,
        "updateContext": null
      },
      "value": "=",
      "start": 330,
      "end": 331,
      "loc": {
        "start": {
          "line": 11,
          "column": 18
        },
        "end": {
          "line": 11,
          "column": 19
        }
      }
    },
    {
      "type": {
        "label": "{",
        "beforeExpr": true,
        "startsExpr": true,
        "rightAssociative": false,
        "isLoop": false,
        "isAssign": false,
        "prefix": false,
        "postfix": false,
        "binop": null
      },
      "start": 332,
      "end": 333,
      "loc": {
        "start": {
          "line": 11,
          "column": 20
        },
        "end": {
          "line": 11,
          "column": 21
        }
      }
    },
    {
      "type": {
        "label": "name",
        "beforeExpr": false,
        "startsExpr": true,
        "rightAssociative": false,
        "isLoop": false,
        "isAssign": false,
        "prefix": false,
        "postfix": false,
        "binop": null
      },
      "value": "start",
      "start": 333,
      "end": 338,
      "loc": {
        "start": {
          "line": 11,
          "column": 21
        },
        "end": {
          "line": 11,
          "column": 26
        }
      }
    },
    {
      "type": {
        "label": ",",
        "beforeExpr": true,
        "startsExpr": false,
        "rightAssociative": false,
        "isLoop": false,
        "isAssign": false,
        "prefix": false,
        "postfix": false,
        "binop": null,
        "updateContext": null
      },
      "start": 338,
      "end": 339,
      "loc": {
        "start": {
          "line": 11,
          "column": 26
        },
        "end": {
          "line": 11,
          "column": 27
        }
      }
    },
    {
      "type": {
        "label": "name",
        "beforeExpr": false,
        "startsExpr": true,
        "rightAssociative": false,
        "isLoop": false,
        "isAssign": false,
        "prefix": false,
        "postfix": false,
        "binop": null
      },
      "value": "end",
      "start": 340,
      "end": 343,
      "loc": {
        "start": {
          "line": 11,
          "column": 28
        },
        "end": {
          "line": 11,
          "column": 31
        }
      }
    },
    {
      "type": {
        "label": ":",
        "beforeExpr": true,
        "startsExpr": false,
        "rightAssociative": false,
        "isLoop": false,
        "isAssign": false,
        "prefix": false,
        "postfix": false,
        "binop": null,
        "updateContext": null
      },
      "start": 343,
      "end": 344,
      "loc": {
        "start": {
          "line": 11,
          "column": 31
        },
        "end": {
          "line": 11,
          "column": 32
        }
      }
    },
    {
      "type": {
        "label": "name",
        "beforeExpr": false,
        "startsExpr": true,
        "rightAssociative": false,
        "isLoop": false,
        "isAssign": false,
        "prefix": false,
        "postfix": false,
        "binop": null
      },
      "value": "start",
      "start": 345,
      "end": 350,
      "loc": {
        "start": {
          "line": 11,
          "column": 33
        },
        "end": {
          "line": 11,
          "column": 38
        }
      }
    },
    {
      "type": {
        "label": "+/-",
        "beforeExpr": true,
        "startsExpr": true,
        "rightAssociative": false,
        "isLoop": false,
        "isAssign": false,
        "prefix": true,
        "postfix": false,
        "binop": 9,
        "updateContext": null
      },
      "value": "+",
      "start": 351,
      "end": 352,
      "loc": {
        "start": {
          "line": 11,
          "column": 39
        },
        "end": {
          "line": 11,
          "column": 40
        }
      }
    },
    {
      "type": {
        "label": "num",
        "beforeExpr": false,
        "startsExpr": true,
        "rightAssociative": false,
        "isLoop": false,
        "isAssign": false,
        "prefix": false,
        "postfix": false,
        "binop": null,
        "updateContext": null
      },
      "value": 1,
      "start": 353,
      "end": 354,
      "loc": {
        "start": {
          "line": 11,
          "column": 41
        },
        "end": {
          "line": 11,
          "column": 42
        }
      }
    },
    {
      "type": {
        "label": "}",
        "beforeExpr": false,
        "startsExpr": false,
        "rightAssociative": false,
        "isLoop": false,
        "isAssign": false,
        "prefix": false,
        "postfix": false,
        "binop": null
      },
      "start": 354,
      "end": 355,
      "loc": {
        "start": {
          "line": 11,
          "column": 42
        },
        "end": {
          "line": 11,
          "column": 43
        }
      }
    },
    {
      "type": {
        "label": ";",
        "beforeExpr": true,
        "startsExpr": false,
        "rightAssociative": false,
        "isLoop": false,
        "isAssign": false,
        "prefix": false,
        "postfix": false,
        "binop": null,
        "updateContext": null
      },
      "start": 355,
      "end": 356,
      "loc": {
        "start": {
          "line": 11,
          "column": 43
        },
        "end": {
          "line": 11,
          "column": 44
        }
      }
    },
    {
      "type": {
        "label": "throw",
        "keyword": "throw",
        "beforeExpr": true,
        "startsExpr": false,
        "rightAssociative": false,
        "isLoop": false,
        "isAssign": false,
        "prefix": false,
        "postfix": false,
        "binop": null,
        "updateContext": null
      },
      "value": "throw",
      "start": 360,
      "end": 365,
      "loc": {
        "start": {
          "line": 12,
          "column": 3
        },
        "end": {
          "line": 12,
          "column": 8
        }
      }
    },
    {
      "type": {
        "label": "new",
        "keyword": "new",
        "beforeExpr": true,
        "startsExpr": true,
        "rightAssociative": false,
        "isLoop": false,
        "isAssign": false,
        "prefix": false,
        "postfix": false,
        "binop": null,
        "updateContext": null
      },
      "value": "new",
      "start": 366,
      "end": 369,
      "loc": {
        "start": {
          "line": 12,
          "column": 9
        },
        "end": {
          "line": 12,
          "column": 12
        }
      }
    },
    {
      "type": {
        "label": "name",
        "beforeExpr": false,
        "startsExpr": true,
        "rightAssociative": false,
        "isLoop": false,
        "isAssign": false,
        "prefix": false,
        "postfix": false,
        "binop": null
      },
      "value": "ASCIIDecodeError",
      "start": 370,
      "end": 386,
      "loc": {
        "start": {
          "line": 12,
          "column": 13
        },
        "end": {
          "line": 12,
          "column": 29
        }
      }
    },
    {
      "type": {
        "label": "(",
        "beforeExpr": true,
        "startsExpr": true,
        "rightAssociative": false,
        "isLoop": false,
        "isAssign": false,
        "prefix": false,
        "postfix": false,
        "binop": null
      },
      "start": 386,
      "end": 387,
      "loc": {
        "start": {
          "line": 12,
          "column": 29
        },
        "end": {
          "line": 12,
          "column": 30
        }
      }
    },
    {
      "type": {
        "label": "name",
        "beforeExpr": false,
        "startsExpr": true,
        "rightAssociative": false,
        "isLoop": false,
        "isAssign": false,
        "prefix": false,
        "postfix": false,
        "binop": null
      },
      "value": "reason",
      "start": 387,
      "end": 393,
      "loc": {
        "start": {
          "line": 12,
          "column": 30
        },
        "end": {
          "line": 12,
          "column": 36
        }
      }
    },
    {
      "type": {
        "label": ",",
        "beforeExpr": true,
        "startsExpr": false,
        "rightAssociative": false,
        "isLoop": false,
        "isAssign": false,
        "prefix": false,
        "postfix": false,
        "binop": null,
        "updateContext": null
      },
      "start": 393,
      "end": 394,
      "loc": {
        "start": {
          "line": 12,
          "column": 36
        },
        "end": {
          "line": 12,
          "column": 37
        }
      }
    },
    {
      "type": {
        "label": "name",
        "beforeExpr": false,
        "startsExpr": true,
        "rightAssociative": false,
        "isLoop": false,
        "isAssign": false,
        "prefix": false,
        "postfix": false,
        "binop": null
      },
      "value": "object",
      "start": 395,
      "end": 401,
      "loc": {
        "start": {
          "line": 12,
          "column": 38
        },
        "end": {
          "line": 12,
          "column": 44
        }
      }
    },
    {
      "type": {
        "label": ",",
        "beforeExpr": true,
        "startsExpr": false,
        "rightAssociative": false,
        "isLoop": false,
        "isAssign": false,
        "prefix": false,
        "postfix": false,
        "binop": null,
        "updateContext": null
      },
      "start": 401,
      "end": 402,
      "loc": {
        "start": {
          "line": 12,
          "column": 44
        },
        "end": {
          "line": 12,
          "column": 45
        }
      }
    },
    {
      "type": {
        "label": "name",
        "beforeExpr": false,
        "startsExpr": true,
        "rightAssociative": false,
        "isLoop": false,
        "isAssign": false,
        "prefix": false,
        "postfix": false,
        "binop": null
      },
      "value": "position",
      "start": 403,
      "end": 411,
      "loc": {
        "start": {
          "line": 12,
          "column": 46
        },
        "end": {
          "line": 12,
          "column": 54
        }
      }
    },
    {
      "type": {
        "label": ")",
        "beforeExpr": false,
        "startsExpr": false,
        "rightAssociative": false,
        "isLoop": false,
        "isAssign": false,
        "prefix": false,
        "postfix": false,
        "binop": null
      },
      "start": 411,
      "end": 412,
      "loc": {
        "start": {
          "line": 12,
          "column": 54
        },
        "end": {
          "line": 12,
          "column": 55
        }
      }
    },
    {
      "type": {
        "label": ";",
        "beforeExpr": true,
        "startsExpr": false,
        "rightAssociative": false,
        "isLoop": false,
        "isAssign": false,
        "prefix": false,
        "postfix": false,
        "binop": null,
        "updateContext": null
      },
      "start": 412,
      "end": 413,
      "loc": {
        "start": {
          "line": 12,
          "column": 55
        },
        "end": {
          "line": 12,
          "column": 56
        }
      }
    },
    {
      "type": {
        "label": "}",
        "beforeExpr": false,
        "startsExpr": false,
        "rightAssociative": false,
        "isLoop": false,
        "isAssign": false,
        "prefix": false,
        "postfix": false,
        "binop": null
      },
      "start": 416,
      "end": 417,
      "loc": {
        "start": {
          "line": 13,
          "column": 2
        },
        "end": {
          "line": 13,
          "column": 3
        }
      }
    },
    {
      "type": {
        "label": "yield",
        "keyword": "yield",
        "beforeExpr": true,
        "startsExpr": true,
        "rightAssociative": false,
        "isLoop": false,
        "isAssign": false,
        "prefix": false,
        "postfix": false,
        "binop": null,
        "updateContext": null
      },
      "value": "yield",
      "start": 421,
      "end": 426,
      "loc": {
        "start": {
          "line": 15,
          "column": 2
        },
        "end": {
          "line": 15,
          "column": 7
        }
      }
    },
    {
      "type": {
        "label": "name",
        "beforeExpr": false,
        "startsExpr": true,
        "rightAssociative": false,
        "isLoop": false,
        "isAssign": false,
        "prefix": false,
        "postfix": false,
        "binop": null
      },
      "value": "byte2char",
      "start": 427,
      "end": 436,
      "loc": {
        "start": {
          "line": 15,
          "column": 8
        },
        "end": {
          "line": 15,
          "column": 17
        }
      }
    },
    {
      "type": {
        "label": "[",
        "beforeExpr": true,
        "startsExpr": true,
        "rightAssociative": false,
        "isLoop": false,
        "isAssign": false,
        "prefix": false,
        "postfix": false,
        "binop": null,
        "updateContext": null
      },
      "start": 436,
      "end": 437,
      "loc": {
        "start": {
          "line": 15,
          "column": 17
        },
        "end": {
          "line": 15,
          "column": 18
        }
      }
    },
    {
      "type": {
        "label": "name",
        "beforeExpr": false,
        "startsExpr": true,
        "rightAssociative": false,
        "isLoop": false,
        "isAssign": false,
        "prefix": false,
        "postfix": false,
        "binop": null
      },
      "value": "b",
      "start": 437,
      "end": 438,
      "loc": {
        "start": {
          "line": 15,
          "column": 18
        },
        "end": {
          "line": 15,
          "column": 19
        }
      }
    },
    {
      "type": {
        "label": "]",
        "beforeExpr": false,
        "startsExpr": false,
        "rightAssociative": false,
        "isLoop": false,
        "isAssign": false,
        "prefix": false,
        "postfix": false,
        "binop": null,
        "updateContext": null
      },
      "start": 438,
      "end": 439,
      "loc": {
        "start": {
          "line": 15,
          "column": 19
        },
        "end": {
          "line": 15,
          "column": 20
        }
      }
    },
    {
      "type": {
        "label": ";",
        "beforeExpr": true,
        "startsExpr": false,
        "rightAssociative": false,
        "isLoop": false,
        "isAssign": false,
        "prefix": false,
        "postfix": false,
        "binop": null,
        "updateContext": null
      },
      "start": 439,
      "end": 440,
      "loc": {
        "start": {
          "line": 15,
          "column": 20
        },
        "end": {
          "line": 15,
          "column": 21
        }
      }
    },
    {
      "type": {
        "label": "++/--",
        "beforeExpr": false,
        "startsExpr": true,
        "rightAssociative": false,
        "isLoop": false,
        "isAssign": false,
        "prefix": true,
        "postfix": true,
        "binop": null
      },
      "value": "++",
      "start": 444,
      "end": 446,
      "loc": {
        "start": {
          "line": 17,
          "column": 2
        },
        "end": {
          "line": 17,
          "column": 4
        }
      }
    },
    {
      "type": {
        "label": "name",
        "beforeExpr": false,
        "startsExpr": true,
        "rightAssociative": false,
        "isLoop": false,
        "isAssign": false,
        "prefix": false,
        "postfix": false,
        "binop": null
      },
      "value": "start",
      "start": 446,
      "end": 451,
      "loc": {
        "start": {
          "line": 17,
          "column": 4
        },
        "end": {
          "line": 17,
          "column": 9
        }
      }
    },
    {
      "type": {
        "label": ";",
        "beforeExpr": true,
        "startsExpr": false,
        "rightAssociative": false,
        "isLoop": false,
        "isAssign": false,
        "prefix": false,
        "postfix": false,
        "binop": null,
        "updateContext": null
      },
      "start": 451,
      "end": 452,
      "loc": {
        "start": {
          "line": 17,
          "column": 9
        },
        "end": {
          "line": 17,
          "column": 10
        }
      }
    },
    {
      "type": {
        "label": "}",
        "beforeExpr": false,
        "startsExpr": false,
        "rightAssociative": false,
        "isLoop": false,
        "isAssign": false,
        "prefix": false,
        "postfix": false,
        "binop": null
      },
      "start": 454,
      "end": 455,
      "loc": {
        "start": {
          "line": 18,
          "column": 1
        },
        "end": {
          "line": 18,
          "column": 2
        }
      }
    },
    {
      "type": {
        "label": "}",
        "beforeExpr": false,
        "startsExpr": false,
        "rightAssociative": false,
        "isLoop": false,
        "isAssign": false,
        "prefix": false,
        "postfix": false,
        "binop": null
      },
      "start": 456,
      "end": 457,
      "loc": {
        "start": {
          "line": 19,
          "column": 0
        },
        "end": {
          "line": 19,
          "column": 1
        }
      }
    },
    {
      "type": {
        "label": "eof",
        "beforeExpr": false,
        "startsExpr": false,
        "rightAssociative": false,
        "isLoop": false,
        "isAssign": false,
        "prefix": false,
        "postfix": false,
        "binop": null,
        "updateContext": null
      },
      "start": 458,
      "end": 458,
      "loc": {
        "start": {
          "line": 20,
          "column": 0
        },
        "end": {
          "line": 20,
          "column": 0
        }
      }
    }
  ]
}